iceorb/__init__.py
iceorb/api.py
iceorb/assets/ai.png
iceorb/assets/favicon.ico
iceorb/assets/human.png
iceorb/assets/iceorb.png
iceorb/iceorb.py
iceorb/scripts.py
iceorb/terminal/favicon.ico
iceorb/terminal/iceorb.png
iceorb/terminal/index.html
iceorb/terminal/jquery-3.7.1.min.js
iceorb/terminal/js.js
iceorb/terminal/style.css
iceorb/ui.py
iceorb-1.1.0.dist-info/METADATA
iceorb-1.1.0.dist-info/WHEEL
iceorb-1.1.0.dist-info/entry_points.txt
iceorb-1.1.0.dist-info/licenses/LICENSE
iceorb-1.1.0.dist-info/RECORD
