Metadata-Version: 2.4
Name: iceorb
Version: 1.1.0
Summary: Ice Orb multi-agent system for open-ended wargames with large language models
License: Apache-2.0
License-File: LICENSE
Author: Daniel Hogan
Author-email: 6313241+dphogan@users.noreply.github.com
Requires-Python: >=3.10
Classifier: License :: OSI Approved :: Apache Software License
Classifier: Programming Language :: Python :: 3
Classifier: Programming Language :: Python :: 3.10
Classifier: Programming Language :: Python :: 3.11
Classifier: Programming Language :: Python :: 3.12
Classifier: Programming Language :: Python :: 3.13
Classifier: Programming Language :: Python :: 3.14
Requires-Dist: accelerate
Requires-Dist: fastapi
Requires-Dist: jupyter
Requires-Dist: langchain
Requires-Dist: langchain-chroma
Requires-Dist: langchain-community
Requires-Dist: langchain-huggingface
Requires-Dist: langchain-openai
Requires-Dist: langchain-text-splitters
Requires-Dist: langgraph
Requires-Dist: llama-cpp-python (>=0.3.8)
Requires-Dist: markdown2
Requires-Dist: nicegui
Requires-Dist: numpy
Requires-Dist: openai
Requires-Dist: platformdirs
Requires-Dist: pydantic
Requires-Dist: pyyaml
Requires-Dist: torch
Requires-Dist: torchvision
Requires-Dist: tqdm
Requires-Dist: transformers
Requires-Dist: twine
Requires-Dist: unstructured
Requires-Dist: uvicorn
Requires-Dist: watchfiles
Project-URL: Homepage, https://github.com/dphogan/iceorb
